agent_service/__init__.py
agent_service/main.py
devops_agent_service_project_2022-1.5.0.dist-info/METADATA
devops_agent_service_project_2022-1.5.0.dist-info/WHEEL
devops_agent_service_project_2022-1.5.0.dist-info/top_level.txt
devops_agent_service_project_2022-1.5.0.dist-info/RECORD
