Metadata-Version: 2.1
Name: devops-agent-service-project-2022
Version: 1.5.0
Summary: UNKNOWN
Home-page: UNKNOWN
License: UNKNOWN
Platform: UNKNOWN
Requires-Dist: fastapi
Requires-Dist: sqlalchemy
Requires-Dist: uvicorn
Requires-Dist: pydantic
Requires-Dist: PyJWT
Requires-Dist: passlib
Requires-Dist: typing
Requires-Dist: psycopg2-binary
Requires-Dist: bcrypt
Requires-Dist: pathlib
Requires-Dist: jinja2
Requires-Dist: requests
